README.txt
setup.py
TracGitLocation.egg-info/PKG-INFO
TracGitLocation.egg-info/SOURCES.txt
TracGitLocation.egg-info/dependency_links.txt
TracGitLocation.egg-info/entry_points.txt
TracGitLocation.egg-info/requires.txt
TracGitLocation.egg-info/top_level.txt
gitlocation/__init__.py
gitlocation/web_ui.py