Metadata-Version: 1.0
Name: TracGitLocation
Version: 1.0
Summary: Provide links to the actual URLs of Git-dwelling items
Home-page: http://trac-hacks.org/wiki/GitLocationPlugin
Author: Andreas Zeidler
Author-email: az@zitc.de
License: GPL
Keywords: trac plugin git
Platform: UNKNOWN
Classifier: Framework :: Trac
Classifier: Development Status :: 5 - Production/Stable
Classifier: Environment :: Web Environment
Classifier: Natural Language :: English
Classifier: Operating System :: OS Independent
Classifier: Programming Language :: Python
